csv_convert/__init__.py
csv_convert-0.0.1.dist-info/DESCRIPTION.rst
csv_convert-0.0.1.dist-info/METADATA
csv_convert-0.0.1.dist-info/RECORD
csv_convert-0.0.1.dist-info/WHEEL
csv_convert-0.0.1.dist-info/metadata.json
csv_convert-0.0.1.dist-info/top_level.txt
